{
	"info": {
		"_postman_id": "db7052df-3441-46a9-b1fb-4f1a94c95043",
		"name": "ReqresIn",
		"schema": "https://schema.getpostman.com/json/collection/v2.1.0/collection.json",
		"_exporter_id": "18621434"
	},
	"item": [
		{
			"name": "GET requests",
			"item": [
				{
					"name": "LIST USERS",
					"event": [
						{
							"listen": "test",
							"script": {
								"exec": [
									"pm.test(\"Status code is 200\", function () {\r",
									"    pm.response.to.have.status(200);\r",
									"});"
								],
								"type": "text/javascript"
							}
						}
					],
					"request": {
						"method": "GET",
						"header": [],
						"url": {
							"raw": "{{url}}/api/users?page=2",
							"host": [
								"{{url}}"
							],
							"path": [
								"api",
								"users"
							],
							"query": [
								{
									"key": "page",
									"value": "2"
								}
							]
						}
					},
					"response": []
				},
				{
					"name": "SINGLE USER",
					"event": [
						{
							"listen": "test",
							"script": {
								"exec": [
									"pm.test(\"Status code is 200\", function () {\r",
									"    pm.response.to.have.status(200);\r",
									"});"
								],
								"type": "text/javascript"
							}
						}
					],
					"request": {
						"method": "GET",
						"header": [],
						"url": {
							"raw": "{{url}}/api/users/2",
							"host": [
								"{{url}}"
							],
							"path": [
								"api",
								"users",
								"2"
							]
						}
					},
					"response": []
				},
				{
					"name": "SINGLE USER NOT FOUND",
					"event": [
						{
							"listen": "test",
							"script": {
								"exec": [
									"pm.test(\"Status code is 404\", function () {\r",
									"    pm.response.to.have.status(404);\r",
									"});"
								],
								"type": "text/javascript"
							}
						}
					],
					"request": {
						"method": "GET",
						"header": [],
						"url": {
							"raw": "{{url}}/api/users/23",
							"host": [
								"{{url}}"
							],
							"path": [
								"api",
								"users",
								"23"
							]
						}
					},
					"response": []
				},
				{
					"name": "LIST <RESOURCE>",
					"event": [
						{
							"listen": "test",
							"script": {
								"exec": [
									"pm.test(\"Status code is 200\", function () {\r",
									"    pm.response.to.have.status(200);\r",
									"});"
								],
								"type": "text/javascript"
							}
						}
					],
					"request": {
						"method": "GET",
						"header": [],
						"url": {
							"raw": "{{url}}/api/unknown",
							"host": [
								"{{url}}"
							],
							"path": [
								"api",
								"unknown"
							]
						}
					},
					"response": []
				},
				{
					"name": "SINGLE <RESOURCE>",
					"event": [
						{
							"listen": "test",
							"script": {
								"exec": [
									"pm.test(\"Status code is 200\", function () {\r",
									"    pm.response.to.have.status(200);\r",
									"});"
								],
								"type": "text/javascript"
							}
						}
					],
					"request": {
						"method": "GET",
						"header": [],
						"url": {
							"raw": "{{url}}/api/unknown/2",
							"host": [
								"{{url}}"
							],
							"path": [
								"api",
								"unknown",
								"2"
							]
						}
					},
					"response": []
				},
				{
					"name": "SINGLE <RESOURCE> NOT FOUND",
					"event": [
						{
							"listen": "test",
							"script": {
								"exec": [
									"pm.test(\"Status code is 404\", function () {\r",
									"    pm.response.to.have.status(404);\r",
									"});"
								],
								"type": "text/javascript"
							}
						}
					],
					"request": {
						"method": "GET",
						"header": [],
						"url": {
							"raw": "{{url}}/api/unknown/23",
							"host": [
								"{{url}}"
							],
							"path": [
								"api",
								"unknown",
								"23"
							]
						}
					},
					"response": []
				},
				{
					"name": "DELAYED RESPONSE",
					"event": [
						{
							"listen": "test",
							"script": {
								"exec": [
									"pm.test(\"Status code is 200\", function () {\r",
									"    pm.response.to.have.status(200);\r",
									"});"
								],
								"type": "text/javascript"
							}
						}
					],
					"request": {
						"method": "GET",
						"header": [],
						"url": {
							"raw": "{{url}}/api/users?delay=3",
							"host": [
								"{{url}}"
							],
							"path": [
								"api",
								"users"
							],
							"query": [
								{
									"key": "delay",
									"value": "3"
								}
							]
						}
					},
					"response": []
				}
			]
		},
		{
			"name": "POST requests",
			"item": [
				{
					"name": "CREATE",
					"event": [
						{
							"listen": "test",
							"script": {
								"exec": [
									"pm.test(\"Status code is 201\", function () {\r",
									"    pm.response.to.have.status(201);\r",
									"});\r",
									"\r",
									"pm.test(\"Body matches string\", function () {\r",
									"    pm.expect(pm.response.text()).to.include('name', 'job', 'id', 'createdAt');\r",
									"});\r",
									""
								],
								"type": "text/javascript"
							}
						}
					],
					"request": {
						"method": "POST",
						"header": [],
						"body": {
							"mode": "raw",
							"raw": "{\r\n    \"name\": \"morpheus\",\r\n    \"job\": \"leader\"\r\n}",
							"options": {
								"raw": {
									"language": "json"
								}
							}
						},
						"url": {
							"raw": "{{url}}/api/users",
							"host": [
								"{{url}}"
							],
							"path": [
								"api",
								"users"
							]
						}
					},
					"response": []
				},
				{
					"name": "REGISTER - SUCCESSFUL",
					"event": [
						{
							"listen": "test",
							"script": {
								"exec": [
									"pm.test(\"Status code is 200\", function () {\r",
									"    pm.response.to.have.status(200);\r",
									"});\r",
									"\r",
									"pm.test(\"Body matches string\", function () {\r",
									"    pm.expect(pm.response.text()).to.include('id', 'token');\r",
									"});\r",
									""
								],
								"type": "text/javascript"
							}
						}
					],
					"request": {
						"method": "POST",
						"header": [],
						"body": {
							"mode": "raw",
							"raw": "{\r\n    \"email\": \"eve.holt@reqres.in\",\r\n    \"password\": \"pistol\"\r\n}",
							"options": {
								"raw": {
									"language": "json"
								}
							}
						},
						"url": {
							"raw": "{{url}}/api/register",
							"host": [
								"{{url}}"
							],
							"path": [
								"api",
								"register"
							]
						}
					},
					"response": []
				},
				{
					"name": "REGISTER - UNSUCCESSFUL",
					"event": [
						{
							"listen": "test",
							"script": {
								"exec": [
									"pm.test(\"Status code is 400\", function () {\r",
									"    pm.response.to.have.status(400);\r",
									"});\r",
									"\r",
									"pm.test(\"Body matches string\", function () {\r",
									"    pm.expect(pm.response.text()).to.include(\"Missing password\");\r",
									"});"
								],
								"type": "text/javascript"
							}
						}
					],
					"request": {
						"method": "POST",
						"header": [],
						"body": {
							"mode": "raw",
							"raw": "{\r\n    \"email\": \"sydney@fife\"\r\n}",
							"options": {
								"raw": {
									"language": "json"
								}
							}
						},
						"url": {
							"raw": "{{url}}/api/register",
							"host": [
								"{{url}}"
							],
							"path": [
								"api",
								"register"
							]
						}
					},
					"response": []
				},
				{
					"name": "LOGIN - SUCCESSFUL",
					"event": [
						{
							"listen": "test",
							"script": {
								"exec": [
									"pm.test(\"Status code is 200\", function () {\r",
									"    pm.response.to.have.status(200);\r",
									"});\r",
									"\r",
									"pm.test(\"Body matches string\", function () {\r",
									"    pm.expect(pm.response.text()).to.include(\"token\");\r",
									"});"
								],
								"type": "text/javascript"
							}
						}
					],
					"request": {
						"method": "POST",
						"header": [],
						"body": {
							"mode": "raw",
							"raw": "{\r\n    \"email\": \"eve.holt@reqres.in\",\r\n    \"password\": \"cityslicka\"\r\n}",
							"options": {
								"raw": {
									"language": "json"
								}
							}
						},
						"url": {
							"raw": "{{url}}/api/login",
							"host": [
								"{{url}}"
							],
							"path": [
								"api",
								"login"
							]
						}
					},
					"response": []
				},
				{
					"name": "LOGIN - UNSUCCESSFUL",
					"event": [
						{
							"listen": "test",
							"script": {
								"exec": [
									"pm.test(\"Status code is 400\", function () {\r",
									"    pm.response.to.have.status(400);\r",
									"});\r",
									"\r",
									"pm.test(\"Body matches string\", function () {\r",
									"    pm.expect(pm.response.text()).to.include(\"Missing password\");\r",
									"});"
								],
								"type": "text/javascript"
							}
						}
					],
					"request": {
						"method": "POST",
						"header": [],
						"body": {
							"mode": "raw",
							"raw": "{\r\n    \"email\": \"peter@klaven\"\r\n}",
							"options": {
								"raw": {
									"language": "json"
								}
							}
						},
						"url": {
							"raw": "{{url}}/api/login",
							"host": [
								"{{url}}"
							],
							"path": [
								"api",
								"login"
							]
						}
					},
					"response": []
				}
			]
		},
		{
			"name": "PUT requests",
			"item": [
				{
					"name": "UPDATE",
					"event": [
						{
							"listen": "test",
							"script": {
								"exec": [
									"pm.test(\"Status code is 200\", function () {\r",
									"    pm.response.to.have.status(200);\r",
									"});\r",
									"\r",
									"pm.test(\"Body matches string\", function () {\r",
									"    pm.expect(pm.response.text()).to.include('name', 'job', 'updatedAt');\r",
									"});"
								],
								"type": "text/javascript"
							}
						}
					],
					"request": {
						"method": "PUT",
						"header": [],
						"body": {
							"mode": "raw",
							"raw": "{\r\n    \"name\": \"morpheus\",\r\n    \"job\": \"zion resident\"\r\n}",
							"options": {
								"raw": {
									"language": "json"
								}
							}
						},
						"url": {
							"raw": "{{url}}/api/users/2",
							"host": [
								"{{url}}"
							],
							"path": [
								"api",
								"users",
								"2"
							]
						}
					},
					"response": []
				}
			]
		},
		{
			"name": "PATCH requests",
			"item": [
				{
					"name": "PARTIAL UPDATE",
					"event": [
						{
							"listen": "test",
							"script": {
								"exec": [
									"pm.test(\"Status code is 200\", function () {\r",
									"    pm.response.to.have.status(200);\r",
									"});\r",
									"\r",
									"pm.test(\"Body matches string\", function () {\r",
									"    pm.expect(pm.response.text()).to.include('name', 'job', 'updatedAt');\r",
									"});"
								],
								"type": "text/javascript"
							}
						}
					],
					"request": {
						"method": "PATCH",
						"header": [],
						"body": {
							"mode": "formdata",
							"formdata": [
								{
									"key": "name",
									"value": "morpheus",
									"type": "text"
								},
								{
									"key": "job",
									"value": "zion resident",
									"type": "text"
								}
							]
						},
						"url": {
							"raw": "{{url}}/api/users/2",
							"host": [
								"{{url}}"
							],
							"path": [
								"api",
								"users",
								"2"
							]
						}
					},
					"response": []
				}
			]
		},
		{
			"name": "DELETE requests",
			"item": [
				{
					"name": "DELETE",
					"event": [
						{
							"listen": "test",
							"script": {
								"exec": [
									"pm.test(\"Status code is 204\", function () {\r",
									"    pm.response.to.have.status(204);\r",
									"});"
								],
								"type": "text/javascript"
							}
						}
					],
					"request": {
						"method": "DELETE",
						"header": [],
						"url": {
							"raw": "{{url}}/api/users/2",
							"host": [
								"{{url}}"
							],
							"path": [
								"api",
								"users",
								"2"
							]
						}
					},
					"response": []
				}
			]
		}
	]
}